mcp_get_weather_http_evan/__init__.py
mcp_get_weather_http_evan/__main__.py
mcp_get_weather_http_evan/server.py
mcp_get_weather_http_evan-1.1.0.dist-info/METADATA
mcp_get_weather_http_evan-1.1.0.dist-info/WHEEL
mcp_get_weather_http_evan-1.1.0.dist-info/entry_points.txt
mcp_get_weather_http_evan-1.1.0.dist-info/top_level.txt
mcp_get_weather_http_evan-1.1.0.dist-info/RECORD
